[{"setting:blockPlugins":"true"},{"setting:blockGclid":"true"},{"setting:preventWebrtcLeak":"true"},{"setting:blockFbclid":"true"},{"setting:settingsExport":"false"},{"setting:blockAds":"true"},{"setting:settingsImport":"false"},{"setting:blockUtm":"true"},{"customProxy":"[]"},{"customUserAgent":"default"},{"setting:autoConnect":"true"},{"setting:locationWarp":"false"},{"setting:excludeMode":"false"},{"setting:blockMalware":"true"},{"setting:toggleTheme":"false"},{"setting:blockTrackers":"true"},{"setting:languageWarp":"false"},{"theme":"white"},{"setting:blockSocial":"false"},{"setting:customProxy":"false"},{"setting:timeWarp":"false"},{"smartLocation":"{\"sites\":[]}"},{"setting:rememberMe":"true"},{"setting:smartLocation":"false"},{"autoExclude":"{\"sites\":[{\"url\":\"forum.vital.audio\",\"pic\":\"https://vitalpublic.s3.dualstack.us-west-2.amazonaws.com/optimized/1X/9ee7f90d38dd0dfbd330ba62a8efb887eb39cfcd_2_32x32.png\"},{\"url\":\"splice.com\",\"pic\":\"https://splice.com/7fc3c0b839df666df0ebdb25f5e15438.png\"},{\"url\":\"www.makeuseof.com\",\"pic\":null},{\"url\":\"leechall.com\",\"pic\":\"https://leechall.com/img/favicon.png\"},{\"url\":\"www.deepbrid.com\",\"pic\":\"https://www.deepbrid.com/favicon.ico\"},{\"url\":\"mp3.pm\",\"pic\":\"https://mp3.pm/favicon.ico\"},{\"url\":\"rapidgator.net\",\"pic\":\"https://rapidgator.net/favicon.ico\"},{\"url\":\"leechpremium.net\",\"pic\":\"https://leechpremium.net/images/favicon.ico\"},{\"url\":\"harrisonconsoles.com\",\"pic\":null},{\"url\":\"songtr.ee\",\"pic\":\"https://songtr.ee/img/songtree-favicon.png\"},{\"url\":\"byjus.com\",\"pic\":\"https://cdn1.byjus.com/byjusweb/img/favicon-32x32.png\"},{\"url\":\"s82.rapidgator.net\",\"pic\":null},{\"url\":\"mail.google.com\",\"pic\":\"https://ssl.gstatic.com/ui/v1/icons/mail/rfr/gmail.ico\"},{\"url\":\"s100.rapidgator.net\",\"pic\":null},{\"url\":\"equipboard.com\",\"pic\":\"https://equipboard.com/favicon.ico\"},{\"url\":\"*.1k.by\",\"pic\":null},{\"url\":\"archive.4plebs.org\",\"pic\":null},{\"url\":\"4plebs.org\",\"pic\":null},{\"url\":\"s103.rapidgator.net\",\"pic\":null},{\"url\":\"www.tiktok.com\",\"pic\":\"https://lf16-tiktok-web.ttwstatic.com/obj/tiktok-web-common-sg/mtact/static/images/logo_144c91a.png\"},{\"url\":\"rutracker.org\",\"pic\":\"http://rutracker.org/favicon.ico\"},{\"url\":\"www.instagram.com\",\"pic\":\"https://static.cdninstagram.com/rsrc.php/yS/r/f_5NUHW7AZC.ico\"},{\"url\":\"gmail.com\",\"pic\":null},{\"url\":\"*.vk.com\",\"pic\":null}]}"},{"setting:blockCookies":"true"},{"setting:languageDropdownBuilder":"false"},{"setting:maskUserAgent":"false"},{"setting:debugMode":"false"},{"setting:allowExtensionNotifications":"false"}]